hypernodes/__init__.py
hypernodes/batch_adapter.py
hypernodes/cache.py
hypernodes/callbacks.py
hypernodes/decorators.py
hypernodes/dual_node.py
hypernodes/engines.py
hypernodes/exceptions.py
hypernodes/graph_builder.py
hypernodes/hypernode.py
hypernodes/map_planner.py
hypernodes/node.py
hypernodes/node_execution.py
hypernodes/orchestrator.py
hypernodes/pipeline.py
hypernodes/pipeline_node.py
hypernodes/protocols.py
hypernodes/sequential_engine.py
hypernodes/visualization.py
hypernodes/integrations/__init__.py
hypernodes/integrations/daft/__init__.py
hypernodes/integrations/daft/codegen.py
hypernodes/integrations/daft/engine.py
hypernodes/integrations/daft/operations.py
hypernodes/integrations/dask/README.md
hypernodes/integrations/dask/__init__.py
hypernodes/integrations/dask/engine.py
hypernodes/telemetry/__init__.py
hypernodes/telemetry/environment.py
hypernodes/telemetry/progress.py
hypernodes/telemetry/tracing.py
hypernodes/telemetry/waterfall.py
hypernodes-0.4.0.dist-info/METADATA
hypernodes-0.4.0.dist-info/WHEEL
hypernodes-0.4.0.dist-info/licenses/LICENSE
hypernodes-0.4.0.dist-info/RECORD
