Metadata-Version: 2.4
Name: hypernodes
Version: 0.4.0
Summary: A hierarchical, modular pipeline system for ML/AI workflows
Project-URL: Homepage, https://github.com/gilad-rubin/hypernodes
Project-URL: Repository, https://github.com/gilad-rubin/hypernodes
Project-URL: Issues, https://github.com/gilad-rubin/hypernodes/issues
Author-email: Gilad Rubin <me@giladrubin.com>
License: MIT
License-File: LICENSE
Keywords: ai,caching,dag,machine-learning,ml,pipeline,workflow
Classifier: Development Status :: 3 - Alpha
Classifier: Intended Audience :: Developers
Classifier: Intended Audience :: Science/Research
Classifier: License :: OSI Approved :: MIT License
Classifier: Programming Language :: Python :: 3
Classifier: Programming Language :: Python :: 3.12
Classifier: Topic :: Scientific/Engineering :: Artificial Intelligence
Classifier: Topic :: Software Development :: Libraries :: Python Modules
Requires-Python: >=3.12
Provides-Extra: all
Requires-Dist: daft>=0.6.11; extra == 'all'
Requires-Dist: graphviz>=0.20; extra == 'all'
Requires-Dist: ipykernel<7; extra == 'all'
Requires-Dist: ipywidgets>=8.1.7; extra == 'all'
Requires-Dist: logfire>=2.0.0; extra == 'all'
Requires-Dist: nbformat>=5.10.4; extra == 'all'
Requires-Dist: plotly>=5.18.0; extra == 'all'
Requires-Dist: rich>=13.0.0; extra == 'all'
Requires-Dist: tqdm>=4.67.1; extra == 'all'
Provides-Extra: daft
Requires-Dist: daft>=0.6.11; extra == 'daft'
Provides-Extra: examples
Requires-Dist: colbert-ai>=0.2.22; extra == 'examples'
Requires-Dist: daft>=0.6.7; extra == 'examples'
Requires-Dist: diskcache>=5.6.3; extra == 'examples'
Requires-Dist: ipykernel>=6.31.0; extra == 'examples'
Requires-Dist: model2vec>=0.7.0; extra == 'examples'
Requires-Dist: numpy>=2.3.4; extra == 'examples'
Requires-Dist: pandas>=2.3.3; extra == 'examples'
Requires-Dist: pydantic>=2.12.3; extra == 'examples'
Requires-Dist: pylate>=1.0.0; extra == 'examples'
Requires-Dist: pytrec-eval>=0.5; extra == 'examples'
Requires-Dist: rank-bm25>=0.2.2; extra == 'examples'
Provides-Extra: modal
Requires-Dist: cloudpickle>=3.0.0; extra == 'modal'
Requires-Dist: modal>=0.64.0; extra == 'modal'
Provides-Extra: notebook
Requires-Dist: ipykernel<7; extra == 'notebook'
Requires-Dist: ipywidgets>=8.1.7; extra == 'notebook'
Requires-Dist: nbformat>=5.10.4; extra == 'notebook'
Provides-Extra: telemetry
Requires-Dist: logfire>=2.0.0; extra == 'telemetry'
Requires-Dist: plotly>=5.18.0; extra == 'telemetry'
Requires-Dist: rich>=13.0.0; extra == 'telemetry'
Requires-Dist: tqdm>=4.67.1; extra == 'telemetry'
Provides-Extra: viz
Requires-Dist: graphviz>=0.20; extra == 'viz'
